{
  "buildFiles": [
    "C:\\flutter\\packages\\flutter_tools\\gradle\\src\\main\\groovy\\CMakeLists.txt"
  ],
  "cleanCommandsComponents": [
    [
      "C:\\Users\\ebrah\\AppData\\Local\\Android\\sdk\\cmake\\3.22.1\\bin\\ninja.exe",
      "-C",
      "D:\\App Development\\Flutter-Painting\\android\\app\\.cxx\\RelWithDebInfo\\35f282s3\\arm64-v8a",
      "clean"
    ]
  ],
  "buildTargetsCommandComponents": [
    "C:\\Users\\ebrah\\AppData\\Local\\Android\\sdk\\cmake\\3.22.1\\bin\\ninja.exe",
    "-C",
    "D:\\App Development\\Flutter-Painting\\android\\app\\.cxx\\RelWithDebInfo\\35f282s3\\arm64-v8a",
    "{LIST_OF_TARGETS_TO_BUILD}"
  ],
  "libraries": {},
  "toolchains": {
    "toolchain": {
      "cCompilerExecutable": "C:\\Users\\ebrah\\AppData\\Local\\Android\\Sdk\\ndk\\26.3.11579264\\toolchains\\llvm\\prebuilt\\windows-x86_64\\bin\\clang.exe",
      "cppCompilerExecutable": "C:\\Users\\ebrah\\AppData\\Local\\Android\\Sdk\\ndk\\26.3.11579264\\toolchains\\llvm\\prebuilt\\windows-x86_64\\bin\\clang++.exe"
    }
  },
  "cFileExtensions": [],
  "cppFileExtensions": []
}